{
  "_cts": {
    "project": {
      "text_blurb": {
        "heading": {
          "config": {
            "patternType": "HEADING",
            "blocks": 1
          }
        },
        "paragraph": {
          "config": {
            "patternType": "PARAGRAPH",
            "blocks": 1
          }
        }
      },
      "headline": {
        "config": {
          "patternType": "HEADING",
          "blocks": 1
        }
      },
      "client": {
        "config": {
          "patternType": "PARAGRAPH",
          "blocks": 1
        }
      },
      "sq_ft": {
        "config": {
          "patternType": "PARAGRAPH",
          "blocks": 1
        }
      },
      "quote": {
        "quote_text": {
          "config": {
            "patternType": "PARAGRAPH",
            "blocks": 1
          }
        }
      },
      "concluding_statement": {
        "config": {
          "patternType": "PARAGRAPH",
          "blocks": 1
        }
      }
    },
    "homepage": {
      "heading": {
        "config": {
          "patternType": "HEADING",
          "blocks": 1
        }
      }
    },
    "sector": {
      "description": {
        "config": {
          "patternType": "PARAGRAPH",
          "blocks": 1
        }
      }
    },
    "specialty": {},
    "projects_page": {},
    "additional_project": {
      "name": {
        "config": {
          "patternType": "PARAGRAPH",
          "blocks": 1
        }
      }
    }
  },
  "slices": {
    "Specialties": {
      "default": {
        "primary": {},
        "items": {}
      }
    },
    "FeaturedProjects": {
      "default": {
        "primary": {},
        "items": {}
      }
    }
  }
}