[
  {
    "variation": "default",
    "version": "sktwi1xtmkfgx8626",
    "items": [
      {
        "headshot": {
          "dimensions": {
            "width": 900,
            "height": 500
          },
          "alt": null,
          "copyright": null,
          "url": "https://images.unsplash.com/photo-1560457079-9a6532ccb118"
        },
        "name": [
          {
            "type": "paragraph",
            "text": "Excepteur qui exercitation est incididunt esse elit do cillum. Qui sit aliqua dolor velit ipsum proident veniam. Nisi reprehenderit laborum eiusmod occaecat.",
            "spans": []
          }
        ],
        "title": [
          {
            "type": "paragraph",
            "text": "Reprehenderit irure reprehenderit tempor culpa commodo sit minim cupidatat voluptate voluptate Lorem est anim id.",
            "spans": []
          }
        ],
        "paragraph": [
          {
            "type": "paragraph",
            "text": "Laboris labore laboris do minim ea ex occaecat ullamco officia.",
            "spans": []
          }
        ]
      }
    ],
    "primary": {
      "team_segment": [
        {
          "type": "paragraph",
          "text": "Pariatur culpa id esse esse reprehenderit excepteur aliquip cupidatat quis ex culpa quis sunt.",
          "spans": []
        }
      ]
    },
    "slice_type": "team_segment"
  }
]