{
  "id": "mock-doc-id",
  "url": null,
  "type": "about_page",
  "href": null,
  "tags": [],
  "first_publication_date": "1970-01-01T00:00:01+0000",
  "last_publication_date": "1970-01-01T00:00:01+0000",
  "slugs": [],
  "linked_documents": [],
  "lang": "en-us",
  "alternate_languages": [],
  "data": {
    "title_text": [
      {
        "type": "heading3",
        "text": "Stood",
        "spans": []
      }
    ],
    "featured_image": {
      "dimensions": {
        "width": 900,
        "height": 500
      },
      "alt": null,
      "copyright": null,
      "url": "https://images.unsplash.com/photo-1525547719571-a2d4ac8945e2"
    },
    "text_blurb_1": [
      {
        "title": [
          {
            "type": "heading6",
            "text": "Harbor",
            "spans": []
          }
        ],
        "paragraph": [
          {
            "type": "paragraph",
            "text": "Sit ad minim in ipsum proident dolor sit incididunt nostrud laborum cupidatat. Sit consequat anim do occaecat sit anim voluptate id id labore non non.",
            "spans": []
          }
        ]
      }
    ],
    "grid_image_1": {
      "dimensions": {
        "width": 900,
        "height": 500
      },
      "alt": null,
      "copyright": null,
      "url": "https://images.unsplash.com/photo-1587905069134-008460d7a636"
    },
    "grid_image_2": {
      "dimensions": {
        "width": 900,
        "height": 500
      },
      "alt": null,
      "copyright": null,
      "url": "https://images.unsplash.com/photo-1591012911207-0dbac31f37da"
    },
    "grid_image_3": {
      "dimensions": {
        "width": 900,
        "height": 500
      },
      "alt": null,
      "copyright": null,
      "url": "https://images.unsplash.com/photo-1496181133206-80ce9b88a853"
    },
    "grid_image_4": {
      "dimensions": {
        "width": 900,
        "height": 500
      },
      "alt": null,
      "copyright": null,
      "url": "https://images.unsplash.com/photo-1606248897732-2c5ffe759c04"
    },
    "text_blurb_2": [
      {
        "title": [
          {
            "type": "heading6",
            "text": "Experience",
            "spans": []
          }
        ],
        "paragraph": [
          {
            "type": "paragraph",
            "text": "Non voluptate commodo non id elit laborum ut sunt eiusmod quis deserunt ea elit. Ad deserunt pariatur enim tempor Lorem voluptate deserunt do exercitation elit excepteur aute. Enim quis labore ut consequat est mollit tempor nisi laborum esse anim.",
            "spans": []
          }
        ]
      }
    ],
    "featured_image_2": {
      "dimensions": {
        "width": 900,
        "height": 500
      },
      "alt": null,
      "copyright": null,
      "url": "https://images.unsplash.com/photo-1545239351-1141bd82e8a6"
    },
    "text_blurb_3": [
      {
        "title": [
          {
            "type": "heading6",
            "text": "Require",
            "spans": []
          }
        ],
        "paragraph": [
          {
            "type": "paragraph",
            "text": "Et voluptate veniam eiusmod enim minim cillum excepteur ex cupidatat nostrud sunt Lorem minim culpa sint. Reprehenderit velit elit ipsum. Duis pariatur et ullamco ullamco excepteur irure pariatur Lorem nisi minim laboris.",
            "spans": []
          }
        ]
      }
    ],
    "leadership": [
      {
        "headshot": {
          "dimensions": {
            "width": 900,
            "height": 500
          },
          "alt": null,
          "copyright": null,
          "url": "https://images.unsplash.com/photo-1596195689404-24d8a8d1c6ea"
        },
        "name": [
          {
            "type": "paragraph",
            "text": "Officia velit quis ex in dolore exercitation tempor. Culpa incididunt eu elit esse pariatur cillum. Sint commodo duis qui velit irure deserunt incididunt mollit ipsum cillum minim deserunt officia.",
            "spans": []
          }
        ],
        "title": [
          {
            "type": "paragraph",
            "text": "Veniam minim qui et id qui irure qui aute id ut deserunt quis id amet commodo. Ipsum est minim ad laborum minim. Qui sit nulla eu et commodo eiusmod incididunt exercitation incididunt ipsum labore enim incididunt do quis.",
            "spans": []
          }
        ],
        "paragraph": [
          {
            "type": "paragraph",
            "text": "Anim aliqua in exercitation incididunt aliquip deserunt laborum laboris irure magna officia sit.",
            "spans": []
          }
        ]
      }
    ],
    "meta_title": [
      {
        "type": "paragraph",
        "text": "In excepteur non qui. Dolor ut proident ea aute est. Aliqua amet ex exercitation incididunt est culpa nisi nostrud laborum ea cupidatat.",
        "spans": []
      }
    ],
    "meta_description": [
      {
        "type": "paragraph",
        "text": "Eu amet eu duis sit quis sunt nisi exercitation id incididunt cupidatat pariatur est. Ex ipsum minim sint. Ullamco in pariatur qui non elit reprehenderit elit aliquip cupidatat eiusmod reprehenderit voluptate anim voluptate dolor.",
        "spans": []
      }
    ],
    "social_meta_title": [
      {
        "type": "paragraph",
        "text": "Exercitation enim commodo Lorem. Ullamco est magna enim anim occaecat enim cupidatat laboris occaecat dolore officia magna incididunt.",
        "spans": []
      }
    ],
    "social_meta_description": [
      {
        "type": "paragraph",
        "text": "Cupidatat consectetur occaecat consectetur ipsum et est id.",
        "spans": []
      }
    ],
    "social_meta_image": {
      "dimensions": {
        "width": 900,
        "height": 500
      },
      "alt": null,
      "copyright": null,
      "url": "https://images.unsplash.com/photo-1547394765-185e1e68f34e"
    }
  }
}